massmailer/__init__.py
massmailer/admin.py
massmailer/forms.py
massmailer/models.py
massmailer/query_parser.py
massmailer/tasks.py
massmailer/urls.py
massmailer/views.py
massmailer/migrations/0001_initial.py
massmailer/migrations/0002_mail_general_model.py
massmailer/migrations/__init__.py
massmailer/static/massmailer/massmailer.css
massmailer/static/massmailer/query-editor.js
massmailer/static/massmailer/template-editor.js
massmailer/static/massmailer/utils.js
massmailer/static/massmailer/vendor/ace.js
massmailer/static/massmailer/vendor/bootstrap.min.css
massmailer/static/massmailer/vendor/bootstrap.min.js
massmailer/static/massmailer/vendor/ext-language_tools.js
massmailer/static/massmailer/vendor/ext-themelist.js
massmailer/static/massmailer/vendor/jquery.min.js
massmailer/static/massmailer/vendor/mode-django.js
massmailer/static/massmailer/vendor/select2.min.css
massmailer/static/massmailer/vendor/select2.min.js
massmailer/static/massmailer/vendor/font-awesome/css/font-awesome.css
massmailer/static/massmailer/vendor/font-awesome/css/font-awesome.css.map
massmailer/static/massmailer/vendor/font-awesome/css/font-awesome.min.css
massmailer/static/massmailer/vendor/font-awesome/fonts/FontAwesome.otf
massmailer/static/massmailer/vendor/font-awesome/fonts/fontawesome-webfont.eot
massmailer/static/massmailer/vendor/font-awesome/fonts/fontawesome-webfont.svg
massmailer/static/massmailer/vendor/font-awesome/fonts/fontawesome-webfont.ttf
massmailer/static/massmailer/vendor/font-awesome/fonts/fontawesome-webfont.woff
massmailer/static/massmailer/vendor/font-awesome/fonts/fontawesome-webfont.woff2
massmailer/templates/massmailer/base.html
massmailer/templates/massmailer/batch-create.html
massmailer/templates/massmailer/batch-emails.html
massmailer/templates/massmailer/batch-list.html
massmailer/templates/massmailer/batch_confirm_delete.html
massmailer/templates/massmailer/common.html
massmailer/templates/massmailer/dashboard.html
django_massmailer-0.6.dist-info/AUTHORS
django_massmailer-0.6.dist-info/LICENSE
django_massmailer-0.6.dist-info/METADATA
django_massmailer-0.6.dist-info/WHEEL
django_massmailer-0.6.dist-info/top_level.txt
django_massmailer-0.6.dist-info/RECORD
