Metadata-Version: 2.1
Name: django-massmailer
Version: 0.6
Summary: A standalone Django app to send templated emails in batch. Features a custom query engine and template editor with preview.
Home-page: UNKNOWN
Author: Association Prologin
Author-email: info@prologin.org
License: GPL3
Project-URL: Source, https://github.com/prologin/django-massmailer/
Project-URL: Issue Tracker, https://github.com/prologin/django-massmailer/issues
Platform: UNKNOWN
Classifier: Environment :: Web Environment
Classifier: License :: OSI Approved :: GNU General Public License v3 (GPLv3)
Classifier: Programming Language :: Python
Classifier: Programming Language :: Python :: 3.6
Classifier: Programming Language :: Python :: 3.7
Classifier: Programming Language :: Python :: 3.8
Classifier: Framework :: Django
Classifier: Framework :: Django :: 2.1
Classifier: Framework :: Django :: 2.2
Classifier: Intended Audience :: Developers
Classifier: Topic :: Communications :: Email
Classifier: Topic :: Internet :: WWW/HTTP
Classifier: Topic :: Internet :: WWW/HTTP :: Dynamic Content
Requires-Dist: babel
Requires-Dist: bleach
Requires-Dist: celery (>4)
Requires-Dist: django-bootstrap-breadcrumbs
Requires-Dist: django-crispy-forms
Requires-Dist: django-reversion
Requires-Dist: django (>=2.1)
Requires-Dist: jinja2
Requires-Dist: markdown
Requires-Dist: pyparsing
